<?xml version="1.0" encoding="UTF-8"?>
<!DOCTYPE hibernate-configuration PUBLIC
		"-//Hibernate/Hibernate Configuration DTD 3.0//EN"
		"http://www.hibernate.org/dtd/hibernate-configuration-3.0.dtd">
<hibernate-configuration>
    <session-factory>
        <property name="hibernate.connection.driver_class">com.mysql.jdbc.Driver</property>
        <property name="hibernate.connection.password">zhangwei</property>
        <property name="hibernate.connection.url">jdbc:mysql://192.168.101.131/parasol_metadata?useUnicode=true&amp;characterEncoding=UTF-8</property>
        <property name="hibernate.connection.username">zhangwei</property>
        <property name="hibernate.dialect">org.hibernate.dialect.MySQLDialect</property>
        <mapping resource="gintong/parasol/metadata/vo/TbCodeRegion.hbm.xml"/>
        
    </session-factory>
</hibernate-configuration>
